<?xml version="1.0" encoding="utf-16"?>
<JOEE xmlns:xsi="http://www.w3.org/2001/XMLSchema-instance" xmlns:xsd="http://www.w3.org/2001/XMLSchema">
  <LotInfo>
    <Index>76800.4587626</Index>
    <EquimentID />
    <LotNo>12321</LotNo>
    <OPID>21312</OPID>
    <DeviceType>5X3.2</DeviceType>
    <Mode>LOAD</Mode>
    <Recipe>5X3.2</Recipe>
    <Version>1.0.0.1</Version>
    <StartTime>2022-05-26T21:20:00.4587626+08:00</StartTime>
    <EndTime>2022-05-26T21:20:14.5297166+08:00</EndTime>
    <RunTime>4</RunTime>
    <StopTime>10</StopTime>
    <AlarmTime>0</AlarmTime>
    <LotQty>12312</LotQty>
    <BinQtyList />
  </LotInfo>
  <DiePakList />
  <AlarmList />
  <DeviceIDList />
  <ICIDList />
</JOEE>